odoo/addons/product_tier_validation/README.rst
odoo/addons/product_tier_validation/__init__.py
odoo/addons/product_tier_validation/__manifest__.py
odoo/addons/product_tier_validation/data/tier_definition.xml
odoo/addons/product_tier_validation/i18n/es.po
odoo/addons/product_tier_validation/i18n/fr.po
odoo/addons/product_tier_validation/i18n/it.po
odoo/addons/product_tier_validation/i18n/product_tier_validation.pot
odoo/addons/product_tier_validation/models/__init__.py
odoo/addons/product_tier_validation/models/product_template.py
odoo/addons/product_tier_validation/models/tier_definition.py
odoo/addons/product_tier_validation/readme/CONFIGURATION.rst
odoo/addons/product_tier_validation/readme/CONTRIBUTORS.rst
odoo/addons/product_tier_validation/readme/DESCRIPTION.rst
odoo/addons/product_tier_validation/readme/INSTALL.rst
odoo/addons/product_tier_validation/readme/USAGE.rst
odoo/addons/product_tier_validation/static/description/icon.png
odoo/addons/product_tier_validation/static/description/index.html
odoo/addons/product_tier_validation/tests/__init__.py
odoo/addons/product_tier_validation/tests/test_product_tier_validation.py
odoo/addons/product_tier_validation/views/product_template_view.xml
odoo14_addon_product_tier_validation-14.0.2.0.2.dist-info/METADATA
odoo14_addon_product_tier_validation-14.0.2.0.2.dist-info/WHEEL
odoo14_addon_product_tier_validation-14.0.2.0.2.dist-info/top_level.txt
odoo14_addon_product_tier_validation-14.0.2.0.2.dist-info/RECORD
